LICENSE
MANIFEST.in
README.md
pypi_instructions.txt
pyproject.toml
requirements.txt
setup.py
orfipy/__init__.py
orfipy/__main__.py
orfipy/findorfs.py
orfipy/orfipy_core.c
orfipy/orfipy_core.pyx
orfipy/translation_tables.py
orfipy/utils.py
orfipy/version.py
orfipy.egg-info/PKG-INFO
orfipy.egg-info/SOURCES.txt
orfipy.egg-info/dependency_links.txt
orfipy.egg-info/entry_points.txt
orfipy.egg-info/requires.txt
orfipy.egg-info/top_level.txt