Metadata-Version: 2.1
Name: orfipy
Version: 0.0.4
Summary: orfipy
Home-page: https://github.com/urmi-21/orfipy
Author: Urminder Singh
Author-email: usingh@iastate.edu
License: UNKNOWN
Platform: UNKNOWN
Classifier: Programming Language :: Python :: 3
Classifier: License :: OSI Approved :: MIT License
Classifier: Operating System :: Unix
Requires-Python: >=3.5
